distracting_control/__init__.py
distracting_control/background.py
distracting_control/camera.py
distracting_control/color.py
distracting_control/gym_env.py
distracting_control/mixins.py
distracting_control/suite.py
distracting_control/suite_utils.py
distracting_control/wrappers.py
gdc/__init__.py
specs/__init__.py
specs/camera_test.py
specs/distracting_control_demo.py
specs/gym_dc-intensity-demo.py
specs/gym_dc_demo.py
specs/gym_dc_test.py
specs/suite_test.py
specs/test_distracting_control.py
distracting_control-0.1.1rc3.dist-info/METADATA
distracting_control-0.1.1rc3.dist-info/WHEEL
distracting_control-0.1.1rc3.dist-info/top_level.txt
distracting_control-0.1.1rc3.dist-info/RECORD
