Metadata-Version: 2.1
Name: distracting-control
Version: 0.1.1rc3
Summary: distractor control suite contains variants of the DeepMind Control suite with visual distraction
Home-page: https://github.com/geyang/distracting_control
Author: Ge Yang<ge.ike.yang@gmail.com>
Author-email: ge.ike.yang@gmail.com
License: UNKNOWN
Platform: UNKNOWN
Requires-Dist: gym
Requires-Dist: dm-control
Requires-Dist: numpy
